{
  "project_info": {
    "project_number": "304123455974",
    "project_id": "resqapp-9d32e",
    "storage_bucket": "resqapp-9d32e.appspot.com"
  },
  "client": [
    {
      "client_info": {
        "mobilesdk_app_id": "1:304123455974:android:3c003a966eb79546bb4e27",
        "android_client_info": {
          "package_name": "com.example.resq"
        }
      },
      "oauth_client": [],
      "api_key": [
        {
          "current_key": "AIzaSyCqywsA84NfmPpTK6a-4g_81trMntCatwc"
        }
      ],
      "services": {
        "appinvite_service": {
          "other_platform_oauth_client": []
        }
      }
    }
  ],
  "configuration_version": "1"
}